Workbook

Sheet Relative Valuation
B2: Comparable Company Valuation
C4: Market Data | I4: Financials | M4: Valuation
B5: Company | C5: Share Price | D5: Shares O/s | E5: Equity Value | F5: Net Debt | G5: Enterprise Value | I5: Revenue | J5: EBITDA | K5: Net Income | M5: EV/Revenue | N5: EV/EBITDA | O5: P/E
B7: ='Raw Data -screener'!C5 -> Cipla | C7: ='Raw Data -screener'!D5 -> 1432.2 | D7: ='Raw Data -screener'!E5 -> 80.79 | E7: ='Raw Data -screener'!F5 -> 115707.44 | F7: ='Raw Data -screener'!I5 -> -693.65 | G7: ='Raw Data -screener'!J5 -> 115013.79 | I7: ='Raw Data -screener'!K5 -> 28324.4 | J7: ='Raw Data -screener'!L5 -> 5296.6628 | K7: ='Raw Data -screener'!M5 -> 3355.68 | M7: =G7/I7 -> 4.0605904 | N7: =G7/J7 -> 21.714387 | O7: =E7/K7 -> 34.48107
B8: ='Raw Data -screener'!C2 -> Sun Pharma.Inds. | C8: ='Raw Data -screener'!D2 -> 1902.4 | D8: ='Raw Data -screener'!E2 -> 239.93 | E8: ='Raw Data -screener'!F2 -> 456442.83 | F8: ='Raw Data -screener'!I2 -> -6975.76 | G8: ='Raw Data -screener'!J2 -> 449467.07 | I8: ='Raw Data -screener'!K2 -> 59910.52 | J8: ='Raw Data -screener'!L2 -> 17847.344 | K8: ='Raw Data -screener'!M2 -> 12117.01 | M8: =G8/I8 -> 7.5023063 | N8: =G8/J8 -> 25.183976 | O8: =E8/K8 -> 37.669593
B9: ='Raw Data -screener'!C3 -> Divi's Lab. | C9: ='Raw Data -screener'!D3 -> 8597 | D9: ='Raw Data -screener'!E3 -> 26.55 | E9: ='Raw Data -screener'!F3 -> 228250.35 | F9: ='Raw Data -screener'!I3 -> -3407 | G9: ='Raw Data -screener'!J3 -> 224843.35 | I9: ='Raw Data -screener'!K3 -> 11230 | J9: ='Raw Data -screener'!L3 -> 3967.559 | K9: ='Raw Data -screener'!M3 -> 2925 | M9: =G9/I9 -> 20.02167 | N9: =G9/J9 -> 56.670449 | O9: =E9/K9 -> 78.034308
B10: ='Raw Data -screener'!C4 -> Torrent Pharma. | C10: ='Raw Data -screener'!D4 -> 4896.5 | D10: ='Raw Data -screener'!E4 -> 38.04 | E10: ='Raw Data -screener'!F4 -> 186262.86 | F10: ='Raw Data -screener'!I4 -> 13860.3 | G10: ='Raw Data -screener'!J4 -> 200123.16 | I10: ='Raw Data -screener'!K4 -> 15723 | J10: ='Raw Data -screener'!L4 -> 5191.7346 | K10: ='Raw Data -screener'!M4 -> 2156 | M10: =G10/I10 -> 12.728052 | N10: =G10/J10 -> 38.546493 | O10: =E10/K10 -> 86.392792
B11: ='Raw Data -screener'!C6 -> Zydus Lifesci. | C11: ='Raw Data -screener'!D6 -> 1120 | D11: ='Raw Data -screener'!E6 -> 99.75 | E11: ='Raw Data -screener'!F6 -> 111720 | F11: ='Raw Data -screener'!I6 -> 11079.4 | G11: ='Raw Data -screener'!J6 -> 122799.4 | I11: ='Raw Data -screener'!K6 -> 28591.7 | J11: ='Raw Data -screener'!L6 -> 8317.3255 | K11: ='Raw Data -screener'!M6 -> 4592.7 | M11: =G11/I11 -> 4.2949317 | N11: =G11/J11 -> 14.764289 | O11: =E11/K11 -> 24.32556
B12: ='Raw Data -screener'!C7 -> Lupin | C12: ='Raw Data -screener'!D7 -> 2201.8 | D12: ='Raw Data -screener'!E7 -> 45.72 | E12: ='Raw Data -screener'!F7 -> 100666.3 | F12: ='Raw Data -screener'!I7 -> 963.28 | G12: ='Raw Data -screener'!J7 -> 101629.58 | I12: ='Raw Data -screener'!K7 -> 29966.58 | J12: ='Raw Data -screener'!L7 -> 9538.3624 | K12: ='Raw Data -screener'!M7 -> 5550.99 | M12: =G12/I12 -> 3.3914306 | N12: =G12/J12 -> 10.654824 | O12: =E12/K12 -> 18.134836
B13: ='Raw Data -screener'!C8 -> Mankind Pharma | C13: ='Raw Data -screener'!D8 -> 2384 | D13: ='Raw Data -screener'!E8 -> 41.3 | E13: ='Raw Data -screener'!F8 -> 98459.2 | F13: ='Raw Data -screener'!I8 -> 5828.77 | G13: ='Raw Data -screener'!J8 -> 104287.97 | I13: ='Raw Data -screener'!K8 -> 14737.88 | J13: ='Raw Data -screener'!L8 -> 3827.4274 | K13: ='Raw Data -screener'!M8 -> 2067.57 | M13: =G13/I13 -> 7.0761853 | N13: =G13/J13 -> 27.247537 | O13: =E13/K13 -> 47.620734
B14: ='Raw Data -screener'!C9 -> Dr Reddy's Labs | C14: ='Raw Data -screener'!D9 -> 1174.7 | D14: ='Raw Data -screener'!E9 -> 83.47 | E14: ='Raw Data -screener'!F9 -> 98052.209 | F14: ='Raw Data -screener'!I9 -> 4385.4 | G14: ='Raw Data -screener'!J9 -> 102437.61 | I14: ='Raw Data -screener'!K9 -> 33227.9 | J14: ='Raw Data -screener'!L9 -> 5140.3561 | K14: ='Raw Data -screener'!M9 -> 3183.3 | M14: =G14/I14 -> 3.0828794 | N14: =G14/J14 -> 19.928115 | O14: =E14/K14 -> 30.802064
B15: ='Raw Data -screener'!C10 -> Laurus Labs | C15: ='Raw Data -screener'!D10 -> 1802 | D15: ='Raw Data -screener'!E10 -> 54.03 | E15: ='Raw Data -screener'!F10 -> 97362.06 | F15: ='Raw Data -screener'!I10 -> 2404.78 | G15: ='Raw Data -screener'!J10 -> 99766.84 | I15: ='Raw Data -screener'!K10 -> 7269.64 | J15: ='Raw Data -screener'!L10 -> 2034.0453 | K15: ='Raw Data -screener'!M10 -> 1090.53 | M15: =G15/I15 -> 13.723766 | N15: =G15/J15 -> 49.048485 | O15: =E15/K15 -> 89.27958
B16: ='Raw Data -screener'!C11 -> Aurobindo Pharma | C16: ='Raw Data -screener'!D11 -> 1621.3 | D16: ='Raw Data -screener'!E11 -> 58.08 | E16: ='Raw Data -screener'!F11 -> 94165.104 | F16: ='Raw Data -screener'!I11 -> -1797.45 | G16: ='Raw Data -screener'!J11 -> 92367.654 | I16: ='Raw Data -screener'!K11 -> 34935.29 | J16: ='Raw Data -screener'!L11 -> 7081.3833 | K16: ='Raw Data -screener'!M11 -> 3710.8 | M16: =G16/I16 -> 2.6439641 | N16: =G16/J16 -> 13.04373 | O16: =E16/K16 -> 25.375958
B18: High | M18: =MAX(M8:M16) -> 20.02167 | N18: =MAX(N8:N16) -> 56.670449 | O18: =MAX(O8:O16) -> 89.27958
B19: 75th Percentile | M19: =QUARTILE(M8:M16,3) -> 12.728052 | N19: =QUARTILE(N8:N16,3) -> 38.546493 | O19: =QUARTILE(O8:O16,3) -> 78.034308
B20: Average | M20: =AVERAGE(M8:M16) -> 8.2739095 | N20: =AVERAGE(N8:N16) -> 28.3431 | O20: =AVERAGE(O8:O16) -> 48.626158
B21: Median | M21: =MEDIAN(M8:M16) -> 7.0761853 | N21: =MEDIAN(N8:N16) -> 25.183976 | O21: =MEDIAN(O8:O16) -> 37.669593
B22: 25th Percentile | M22: =QUARTILE(M8:M16,1) -> 3.3914306 | N22: =QUARTILE(N8:N16,1) -> 14.764289 | O22: =QUARTILE(O8:O16,1) -> 25.375958
B23: Low | M23: =MIN(M8:M16) -> 2.6439641 | N23: =MIN(N8:N16) -> 10.654824 | O23: =MIN(O8:O16) -> 18.134836
B25: Cipla Comparable Valuation | M25: EV/Revenue | N25: EV/EBITDA | O25: P/E
B27: Implied Enterprise Value | M27: =M21*I7 -> 200428.7 | N27: =N21*J7 -> 133391.03 | O27: =O29+O28 -> 125713.45
B28: Net Debt | M28: =$F$7 -> -693.65 | N28: =$F$7 -> -693.65 | O28: =$F$7 -> -693.65
B29: Implied Market Value | M29: =M27-M28 -> 201122.35 | N29: =N27-N28 -> 134084.68 | O29: =O21*K7 -> 126407.1
B30: Shares Outstanding | M30: =$D$7 -> 80.79 | N30: =$D$7 -> 80.79 | O30: =$D$7 -> 80.79
B31: Implies Value per Share | M31: =M29/M30 -> 2489.4461 | N31: =N29/N30 -> 1659.6692 | O31: =O29/O30 -> 1564.6379
B32: Undervalued/Overvalued | M32: =IF(M31>$C$8,"Undervalued","Overvalued") -> Undervalued | N32: =IF(N31>$C$8,"Undervalued","Overvalued") -> Overvalued | O32: =IF(O31>$C$8,"Undervalued","Overvalued") -> Overvalued

Sheet Raw Data -screener
B1: S.No. | C1: Name | D1: CMP Rs. | E1: No. Eq. Shares Cr. | F1: Market Cap | G1: Debt Rs.Cr. | H1: Cash End Rs.Cr. | I1: Net Debt | J1: EV | K1: Sales Rs.Cr. | L1: EBITDA | M1: NP 12M Rs.Cr.
B2: 1 | C2: Sun Pharma.Inds. | D2: 1902.4 | E2: 239.93 | F2: =D2*E2 -> 456442.83 | G2: 4627.32 | H2: 11603.08 | I2: =G2-H2 -> -6975.76 | J2: =+F2+G2-H2 -> 449467.07 | K2: 59910.52 | L2: 17847.344 | M2: 12117.01
B3: 2 | C3: Divi's Lab. | D3: 8597 | E3: 26.55 | F3: =D3*E3 -> 228250.35 | G3: 7 | H3: 3414 | I3: =G3-H3 -> -3407 | J3: =+F3+G3-H3 -> 224843.35 | K3: 11230 | L3: 3967.559 | M3: 2925
B4: 3 | C4: Torrent Pharma. | D4: 4896.5 | E4: 38.04 | F4: =D4*E4 -> 186262.86 | G4: 15025.5 | H4: 1165.2 | I4: =G4-H4 -> 13860.3 | J4: =+F4+G4-H4 -> 200123.16 | K4: 15723 | L4: 5191.7346 | M4: 2156
B5: 4 | C5: Cipla | D5: 1432.2 | E5: 80.79 | F5: =D5*E5 -> 115707.44 | G5: 613.77 | H5: 1307.42 | I5: =G5-H5 -> -693.65 | J5: =+F5+G5-H5 -> 115013.79 | K5: 28324.4 | L5: 5296.6628 | M5: 3355.68
B6: 5 | C6: Zydus Lifesci. | D6: 1120 | E6: 99.75 | F6: =D6*E6 -> 111720 | G6: 12496 | H6: 1416.6 | I6: =G6-H6 -> 11079.4 | J6: =+F6+G6-H6 -> 122799.4 | K6: 28591.7 | L6: 8317.3255 | M6: 4592.7
B7: 6 | C7: Lupin | D7: 2201.8 | E7: 45.72 | F7: =D7*E7 -> 100666.3 | G7: 6616.18 | H7: 5652.9 | I7: =G7-H7 -> 963.28 | J7: =+F7+G7-H7 -> 101629.58 | K7: 29966.58 | L7: 9538.3624 | M7: 5550.99
B8: 7 | C8: Mankind Pharma | D8: 2384 | E8: 41.3 | F8: =D8*E8 -> 98459.2 | G8: 6311.54 | H8: 482.77 | I8: =G8-H8 -> 5828.77 | J8: =+F8+G8-H8 -> 104287.97 | K8: 14737.88 | L8: 3827.4274 | M8: 2067.57
B9: 8 | C9: Dr Reddy's Labs | D9: 1174.7 | E9: 83.47 | F9: =D9*E9 -> 98052.209 | G9: 7734.1 | H9: 3348.7 | I9: =G9-H9 -> 4385.4 | J9: =+F9+G9-H9 -> 102437.61 | K9: 33227.9 | L9: 5140.3561 | M9: 3183.3
B10: 9 | C10: Laurus Labs | D10: 1802 | E10: 54.03 | F10: =D10*E10 -> 97362.06 | G10: 2518.48 | H10: 113.7 | I10: =G10-H10 -> 2404.78 | J10: =+F10+G10-H10 -> 99766.84 | K10: 7269.64 | L10: 2034.0453 | M10: 1090.53
B11: 10 | C11: Aurobindo Pharma | D11: 1621.3 | E11: 58.08 | F11: =D11*E11 -> 94165.104 | G11: 8072.84 | H11: 9870.29 | I11: =G11-H11 -> -1797.45 | J11: =+F11+G11-H11 -> 92367.654 | K11: 34935.29 | L11: 7081.3833 | M11: 3710.8
B12: 11 | C12: Biocon | D12: 415.55 | E12: 162.97 | F12: =D12*E12 -> 67722.183 | G12: 15434.1 | H12: 3193.6 | I12: =G12-H12 -> 12240.5 | J12: =+F12+G12-H12 -> 79962.683 | K12: 17321.1 | L12: 3536.9686 | M12: 416.4
B13: 12 | C13: Glenmark Pharma. | D13: 2317.9 | E13: 28.22 | F13: =D13*E13 -> 65411.138 | G13: 593.53 | H13: 1176.26 | I13: =G13-H13 -> -582.73 | J13: =+F13+G13-H13 -> 64828.408 | K13: 17736.56 | L13: 4795.9658 | M13: 1797.79
... B31: 30 | C31: Astrazeneca Phar | D31: 7415.5 | E31: 2.5 | F31: =D31*E31 -> 18538.75 | G31: 110.66 | H31: 448.62 | I31: =G31-H31 -> -337.96 | J31: =+F31+G31-H31 -> 18200.79 | K31: 2432.06 | L31: 229.82967 | M31: 169.62
